{
    "data": {
        "51729": {
            "ammo": [
                {
                    "damage": [
                        8,
                        11,
                        14
                    ],
                    "penetration": [
                        17,
                        23,
                        29
                    ],
                    "stun": null,
                    "type": "ARMOR_PIERCING"
                },
                {
                    "damage": [
                        8,
                        11,
                        14
                    ],
                    "penetration": [
                        35,
                        46,
                        58
                    ],
                    "stun": null,
                    "type": "ARMOR_PIERCING_CR"
                }
            ],
            "armor": {
                "hull": {
                    "front": 80,
                    "rear": 50,
                    "sides": 50
                },
                "turret": {
                    "front": 80,
                    "rear": 50,
                    "sides": 50
                }
            },
            "engine": {
                "fire_chance": 0.2,
                "name": "Maybach HL 45 P",
                "power": 160,
                "tag": "Maybach_HL45P",
                "tier": 4,
                "weight": 500
            },
            "gun": {
                "aim_time": 1.4,
                "caliber": 20,
                "dispersion": 0.57,
                "fire_rate": 163.64,
                "move_down_arc": 10,
                "move_up_arc": 20,
                "name": "2 cm Kw.K. 38",
                "reload_time": 3.0,
                "tag": "_20mm_KwK_38_L55A",
                "tier": 1,
                "traverse_speed": 44,
                "weight": 70
            },
            "hp": 260,
            "hull_hp": 208,
            "hull_weight": 10800,
            "is_default": true,
            "max_ammo": 400,
            "max_weight": 18850,
            "modules": {
                "engine_id": 5653,
                "gun_id": 11284,
                "radio_id": 791,
                "suspension_id": 13330,
                "turret_id": 10515
            },
            "profile_id": "791-5653-10515-11284-13330",
            "radio": {
                "name": "FuG 6",
                "signal_range": 345,
                "tag": "FuG6",
                "tier": 4,
                "weight": 70
            },
            "siege": null,
            "speed_backward": 12,
            "speed_forward": 31,
            "suspension": {
                "load_limit": 18850,
                "name": "Pz.Kpfw. II Ausf. J",
                "tag": "PzII_ausf_J",
                "tier": 6,
                "traverse_speed": 32,
                "weight": 4200
            },
            "tank_id": 51729,
            "turret": {
                "hp": 52,
                "name": "Pz.Kpfw. II Ausf. J",
                "tag": "PzIIturm_ausf_J",
                "tier": 4,
                "traverse_left_arc": 180,
                "traverse_right_arc": 180,
                "traverse_speed": 40,
                "view_range": 320,
                "weight": 2000
            },
            "weight": 17890
        }
    },
    "meta": {
        "count": 1
    },
    "status": "ok"
}